README.md
setup.py
apollo_client.egg-info/PKG-INFO
apollo_client.egg-info/SOURCES.txt
apollo_client.egg-info/dependency_links.txt
apollo_client.egg-info/not-zip-safe
apollo_client.egg-info/requires.txt
apollo_client.egg-info/top_level.txt
pyapollo/__init__.py
pyapollo/apollo_client.py
pyapollo/exceptions.py
scripts/__init__.py
tests/__init__.py
tests/main.py