Metadata-Version: 2.1
Name: apollo-client
Version: 2.1.2
Summary: a client for apollo 2.0, it's been reformatted!
Home-page: UNKNOWN
Author: Lin Luo / Bruce Liu
Author-email: 15869300264@163.com
License: UNKNOWN
Platform: any
Classifier: Programming Language :: Python :: 3.5
